MANIFEST.in
README.md
setup.py
Grasshopper-stubs/__init__.pyi
Grasshopper-stubs/Documentation/__init__.pyi
Grasshopper-stubs/GUI/__init__.pyi
Grasshopper-stubs/GUI/Alignment/__init__.pyi
Grasshopper-stubs/GUI/Base/__init__.pyi
Grasshopper-stubs/GUI/Canvas/__init__.pyi
Grasshopper-stubs/GUI/Canvas/Interaction/__init__.pyi
Grasshopper-stubs/GUI/Canvas/TagArtists/__init__.pyi
Grasshopper-stubs/GUI/Colours/__init__.pyi
Grasshopper-stubs/GUI/Equations/__init__.pyi
Grasshopper-stubs/GUI/Gradient/__init__.pyi
Grasshopper-stubs/GUI/HTML/__init__.pyi
Grasshopper-stubs/GUI/IconEditor/__init__.pyi
Grasshopper-stubs/GUI/Layout/__init__.pyi
Grasshopper-stubs/GUI/MRU/__init__.pyi
Grasshopper-stubs/GUI/RemotePanel/__init__.pyi
Grasshopper-stubs/GUI/Ribbon/__init__.pyi
Grasshopper-stubs/GUI/Script/__init__.pyi
Grasshopper-stubs/GUI/SettingsControls/__init__.pyi
Grasshopper-stubs/GUI/Stacks/__init__.pyi
Grasshopper-stubs/GUI/StringDisplay/__init__.pyi
Grasshopper-stubs/GUI/Theme/__init__.pyi
Grasshopper-stubs/GUI/Widgets/__init__.pyi
Grasshopper-stubs/Getters/__init__.pyi
Grasshopper-stubs/Kernel/__init__.pyi
Grasshopper-stubs/Kernel/Attributes/__init__.pyi
Grasshopper-stubs/Kernel/Components/__init__.pyi
Grasshopper-stubs/Kernel/Data/__init__.pyi
Grasshopper-stubs/Kernel/Expressions/__init__.pyi
Grasshopper-stubs/Kernel/Geometry/__init__.pyi
Grasshopper-stubs/Kernel/Geometry/ConvexHull/__init__.pyi
Grasshopper-stubs/Kernel/Geometry/Delaunay/__init__.pyi
Grasshopper-stubs/Kernel/Geometry/SpatialTrees/__init__.pyi
Grasshopper-stubs/Kernel/Geometry/Voronoi/__init__.pyi
Grasshopper-stubs/Kernel/Graphs/__init__.pyi
Grasshopper-stubs/Kernel/Parameters/__init__.pyi
Grasshopper-stubs/Kernel/Parameters/Hints/__init__.pyi
Grasshopper-stubs/Kernel/Sorting/__init__.pyi
Grasshopper-stubs/Kernel/Special/__init__.pyi
Grasshopper-stubs/Kernel/Special/SketchElements/__init__.pyi
Grasshopper-stubs/Kernel/Types/__init__.pyi
Grasshopper-stubs/Kernel/Types/Transforms/__init__.pyi
Grasshopper_stubs.egg-info/PKG-INFO
Grasshopper_stubs.egg-info/SOURCES.txt
Grasshopper_stubs.egg-info/dependency_links.txt
Grasshopper_stubs.egg-info/top_level.txt