Metadata-Version: 2.1
Name: Grasshopper-stubs
Version: 7.0.19239
Summary: Stubs for Grasshopper
Home-page: https://github.com/mcneel/pythonstubs
Author: Robert McNeel & Associates
Author-email: steve@mcneel.com
License: UNKNOWN
Platform: UNKNOWN
Classifier: Development Status :: 5 - Production/Stable
Classifier: Intended Audience :: Developers
Classifier: License :: OSI Approved :: MIT License
Classifier: Programming Language :: Python
